requires/__about__.py
requires/__init__.py
requires/__main__.py
requires/core.py
requires/py.typed
requires/shed.py
requires-0.12.1.dist-info/WHEEL
requires-0.12.1.dist-info/METADATA
requires-0.12.1.dist-info/RECORD
