Metadata-Version: 2.3
Name: requires
Version: 0.12.1
Summary: Runtime imports and dependency utils
Keywords: decorator,dgpy,funkify,import,requires
Author: jesse
Author-email: jesse <jesse@dgi.com>
Classifier: Development Status :: 5 - Production/Stable
Classifier: Intended Audience :: Developers
Classifier: License :: OSI Approved :: MIT License
Classifier: Programming Language :: Python
Classifier: Programming Language :: Python :: 3 :: Only
Classifier: Programming Language :: Python :: 3.11
Classifier: Programming Language :: Python :: 3.12
Classifier: Programming Language :: Python :: 3.13
Classifier: Programming Language :: Python :: 3.14
Classifier: Typing :: Typed
Requires-Dist: funkify>=0.7
Requires-Python: >=3.11, <4.0
